{
    "pre-workout": {
        "department" : "healthy",
        "unit": "jar"
    },
    "protien powder":{
        "department": "healthy",
        "unit": "jar"
    },
    "power bar":{
        "department": "healthy",
        "unit": "pack"
    },

    "kaylee mixed nuts":{
        "department": "healthy",
        "unit": "bag"
    },
    "banana chips":{
        "department": "healthy",
        "unit": "bag"
    },


    "anthony HEB meal":{
        "department": "produce",
        "unit": "each"
    },
    "avocado":{
        "department": "produce",
        "unit": "each"
    },
    "avocados":{
        "department": "produce",
        "unit": "bag"
    },
    "anthony salad":{
        "department": "produce",
        "unit": "each"
    },
    "apples":{
        "department": "produce",
        "unit": "each"
    },
    "bananas":{
        "department": "produce",
        "unit": "each"
    },
    "baby carrots":{
        "department": "produce",
        "unit": "bag"
    },
    "baby potato":{
        "department": "produce",
        "unit": "lb"
    },
    "baby spinach":{
        "department": "produce",
        "unit": "bag"
    },
    "blueberries":{
        "department": "produce",
        "unit": "basket"
    },
    "bottle ginger":{
        "department": "produce",
        "unit": "tsp"
    },
    "broccoli":{
        "department": "produce",
        "unit": "head"
    },
    "carrot":{
        "department": "produce",
        "unit": "each"
    },
    "cauliflower":{
        "department": "produce",
        "unit": "head"
    },
    "cherries":{
        "department": "produce",
        "unit": "basket"},

    "cilantro":{
        "department": "produce",
        "unit": "bunch"
    },
    "cucumber":{
        "department": "produce",
        "unit": "each"
    },
    "garlic":{
        "department": "produce",
        "unit": "clove"
    },
    "ginger":{
        "department": "produce",
        "unit": "piece"
    },
    "good ranch":{
        "department": "produce",
        "unit": "bottle"
    },
    "healthy coconut water":{
        "department": "produce",
        "unit": "bottle"
    },
    "jarlic":{
        "department": "produce",
        "unit": "tsp"
    },
    "kaylee HEB meal":{
        "department": "produce",
        "unit": "each"
    },
    "kaylee salad":{
        "department": "produce",
        "unit": "each"
    },
    "large potato":{
        "department": "produce",
        "unit": "each"
    },
    "lemon":{
        "department": "produce",
        "unit": "each"
    },
    "lime":{
        "department": "produce",
        "unit": "each"
    },
    "mushroom":{
        "department": "produce",
        "unit": "box"
    },
    "nectarines":{
        "department": "produce",
        "unit": "each"
    },
    "orange bell pepper":{
        "department": "produce",
        "unit": "each"
    },
    "peaches":{
        "department": "produce",
        "unit": "each"
    },
    "pico de galo":{
        "department": "produce",
        "unit": "tub"
    },
    "pre-cut mixed fruit":{
        "department": "produce",
        "unit": "package"
    },
    "red bell pepper":{
        "department": "produce",
        "unit": "each"
    },
    "rosemary":{
        "department": "produce",
        "unit": "tbsp"
    },
    "salsa":{
        "department": "produce",
        "unit": "tub"
    },
    "green salsa":{
        "department": "produce",
        "unit": "tub"
    },
    "shredded carrots":{
        "department": "produce",
        "unit": "bag"
    },
    "shredded lettuce":{
        "department": "produce",
        "unit": "bag"
    },
    "snow peas":{
        "department": "produce",
        "unit": "bag"
    },
    "spinach":{
        "department": "produce",
        "unit": "bag"
    },
    "strawberries":{
        "department": "produce",
        "unit": "basket"
    },
    "sweet potato":{
        "department": "produce",
        "unit": "each"
    },
    "thyme":{
        "department": "produce",
        "unit": "tbsp"
    },
    "white onion":{
        "department": "produce",
        "unit": "each"
    },
    "yellow bell pepper":{
        "department": "produce",
        "unit": "each"
    },
    "yellow onion":{
        "department": "produce",
        "unit": "each"
    },


    "fish filet": {
        "department": "seafood",
        "unit": "lb"
    },
    "shrimp":{
        "department": "seafood",
        "unit": "bag"
    },

    
    "sour dough bread":{
        "department": "bakery",
    "unit": "loaf"
    },


    "beef steak":{
        "department": "meat",
        "unit": "each"
    },
    "brisket":{
        "department": "meat",
        "unit": "each"
    },
    "chicken breast":{
        "department": "meat",
        "unit": "package"
    },
    "chorizo":{
        "department": "meat",
        "unit": "package"
    },
    "chuck roast":{
        "department": "meat",
        "unit": "lb"
    },
    "ground beef":{
        "department": "meat",
        "unit": "lb"
    },
    "ground turkey": {
        "department": "meat",
        "unit": "lb"
    },
    "pork butt":{
        "department": "meat",
        "unit": "each"
    },
    "stir fry steak":{
        "department": "meat",
        "unit": "lb"
    },


    "american sliced cheese":{
        "department": "refrigeration",
        "unit": "pack"
    },
    "bacon":{
        "department": "refrigeration",
        "unit": "package"
    },
    "blue cheese":{
        "department": "refrigeration",
        "unit": "tub"
    },
    "cotija cheese":{
        "department": "refrigeration",
        "unit": "package"
    },
    "deli cheese":{
        "department": "refrigeration",
        "unit": "package"
    },
    "deli meat":{
        "department": "refrigeration",
        "unit": "package"
    },
    "hot dogs":{
        "department": "refrigeration",
        "unit": "pack"
    },
    "jack cheese":{
        "department": "refrigeration",
        "unit": "block"
    },
    "mixed cheese":{
        "department": "refrigeration",
        "unit": "block"
    },
    "mozzarella":{
        "department": "refrigeration",
        "unit": "block"
    },
    "sausage patties":{
        "department": "refrigeration",
        "unit": "pack"
    },
    "string cheese":{
        "department": "refrigeration",
        "unit": "package"
    },
    "turkey bacon":{
        "department": "refrigeration",
        "unit": "package"
    },
    "white cheddar":{
        "department": "refrigeration",
        "unit": "block"
    },


    "beer":{
        "department": "aisle 2",
        "unit": "6er"
    },
    "Danny beers":{
        "department": "aisle 2",
        "unit": "6er"
    },

    "a loaf of bread":{
        "department": "aisle 3",
        "unit": "loaf"
    },
    "black olives":{
        "department": "aisle 3",
        "unit": "can"
    },
    "corn tortillas":{
        "department": "aisle 3",
        "unit": "package"
    },
    "english muffins":{
        "department": "aisle 3",
        "unit": "package"
    },
    "flour tortillas":{
        "department": "aisle 3",
        "unit": "package"
    },
    "green enchilada sauce":{
        "department": "aisle 3",
        "unit": "can"
    },
    "hot dog buns":{
        "department": "asile 3",
        "unit": "pack"
    },
    "red enchilada sauce":{
        "department": "aisle 3",
        "unit": "can"
    },
    "sliced pickles":{
        "department":"aisle 3",
        "unit": "jar"
    },
    "tapatio": {
        "department": "aisle 3",
        "unit": "tbsp"
    },
    "tortillas":{
        "department": "aisle 3",
        "unit": "package"
    },
    "whole pickles":{
        "department":"aisle 3",
        "unit": "jar"
    },
    


    "bbq sauce":{
        "department": "aisle 4",
        "unit": "jar"
    },
    "croutons": {
        "department":"aisle 4",
        "unit": "bag"
    },
    "baby corn":{
        "department": "aisle 4",
        "unit": "can"
    },
    "bacon bits":{
        "department": "aisle 4",
        "unit": "jar"
    },
    "furikake":{
        "department": "aisle 4",
        "unit": "tbsp"
    },
    "low sodium soy sauce":{
        "department": "aisle 4",
        "unit": "tbsp"
    },
    "rice wine":{
        "department": "aisle 4",
        "unit": "tbsp"
    },
    "sea weed": {
        "department": "aisle 4",
        "unit": "pack"
    },
    "soy sauce":{
        "department": "aisle 4",
        "unit": "tbsp"
    },
    "stir fry noodles":{
        "department": "aisle 4",
        "unit": "package"
    },
    "sesame oil":{
        "department": "aisle 4",
        "unit": "tbsp"
    },
    "tortilla strips":{
        "department": "aisle 4",
        "unit": "bag"
    },


    "honey":{
        "department": "aisle 5",
        "unit": "cup"
    },
    "spaghetti noodles":{
        "department": "aisle 5",
        "unit": "package"
    },
    "spaghetti sauce":{
        "department": "aisle 5",
        "unit": "jar"
    },
    "white rice":{
        "department": "aisle 5",
        "unit": "cup"
    },
    "mac & cheese":{
        "department": "aisle 5",
        "unit": "box"
    },
    

    "anthony soup":{
        "department": "aisle 6",
        "unit": "can"
    },
    "black beans":{
        "department":"aisle 6",
        "unit": "can"
    },
    "black or pinto beans":{
        "department":"aisle 6",
        "unit": "can"
    },
    "beef broth":{
        "department": "aisle 6",
        "unit": "cup"
    },
    "enchilada/tortilla soup":{
        "department": "aisle 6",
        "unit": "jar"
    },
    "hormel chili":{
        "department": "aisle 6",
        "unit": "can"
    },
    "kaylee soup":{
        "department": "aisle 6",
        "unit": "can"
    },
    "kidney beans":{
        "department":"aisle 6",
        "unit": "can"
    },
    "low sodium chicken broth":{
        "department": "aisle 6",
        "unit": "box"
    },
    "navy beans":{
        "department": "aisle 6",
        "unit": "can"
    },
    "pinto beans":{
        "department": "aisle 6",
        "unit": "can"
    },
    "refried beans":{
        "department": "aisle 6",
        "unit": "can"
    },
    "spam":{
        "department": "aisle 6",
        "unit": "can"
    },
    "tomato sauce 8oz":{
        "department": "aisle 6",
        "unit": "can"
    },



    
    "brisket rub":{
        "department": "aisle 7",
        "unit": "bottle"
    },
    "corn starch":{
        "department": "aisle 7",
        "unit": "tbsp"
    },
    "dash":{
        "department": "aisle 7",
        "unit": "tbsp"
    },
    "garlic powder": {
        "department": "aisle 7",
        "unit": "tsp"
    },
    "kosher salt": {
        "department": "aisle 7",
        "unit": "tsp"
    },
    "light brown sugar":{
        "department": "aisle 7",
        "unit": "bag"
    }, 
    "olive oil": {
        "department": "aisle 7",
        "unit": "tbsp"
    },
    "onion powder":{
        "department" : "aisle 7",
        "unit": "tsp"
    },
    "paprika": {
        "department": "aisle 7",
        "unit": "tsp"
    },
    "pork rub":{
        "department": "aisle 7",
        "unit": "bottle"
    },
    "red pepper flakes":{
        "department": "aisle 7",
        "unit": "bottle"
    },
    "sesame seeds":{
        "department": "aisle 7",
        "unit": "tbsp"
    },
    "sugar":{
        "department": "aisle 7",
        "unit": "cup"
    },
    "worcestershire sauce":{
        "department": "aisle 7",
        "unit": "tbsp"
    },
    "chili packet":{
        "department": "aisle 7",
        "unit": "each"
    },
    "taco seasoning packet":{
        "department": "aisle 7",
        "unit": "each"
    },


    "granola":{
        "department": "aisle 8",
        "unit": "bag"
    },
    "italian sausage":{
        "department": "aisle 8",
        "unit": "lb"
    },
    "ground breakfast sausage":{
        "department": "aisle 8",
        "unit": "lb"
    },


    "coffee": {
        "department":"aisle 9",
        "unit": "can"
    },


    "chicharrones":{
        "department": "aisle 10",
        "unit": "bag"
    },
    "microwave popcorn":{
        "department": "aisle 10",
        "unit": "box"
    },
    "mixed nuts":{
        "department": "aisle 10",
        "unit": "jar"
    },
    "potato chips":{
        "department": "aisle 10",
        "unit": "bag"
    },
    "tortilla chips":{
        "department": "aisle 10",
        "unit": "bag"
    },
    "rice cakes":{
        "department": "aisle 10",
        "unit": "bag"
    },


    "gatorade":{
        "department": "aisle 12",
        "unit": "package"
    },
    "monster":{
        "department": "aisle 12",
        "unit": "package"
    },
    "water flavor packet":{
        "department": "aisle 12",
        "unit": "package"
    },


    "butter": {
        "department": "dairy",
        "unit": "tbsp"
    },
    "coffee creamer":{
        "department": "dairy",
        "unit": "jug"
    },
    "eggs":{
        "department": "dairy",
        "unit": "18 pack"
    },
    "greek yogurt":{
        "department": "dairy",
        "unit": "tub"
    },
    "milk":{
        "department": "dairy",
        "unit": "half gallon"
    },
    "sour cream":{
        "department": "dairy",
        "unit": "small tub"
    },
    "yakult":{
        "department": "dairy",
        "unit": "pack"
    },


    "toilet paper":{
        "department": "aisle 23",
        "unit": "package"
    },
    "paper towels":{
        "department": "aisle 23",
        "unit": "package"
    },

    "aluminum foil":{
        "department": "aisle 24",
        "unit": "box"
    },
    "kitchen trash bags":{
        "department": "aisle 24",
        "unit": "box"
    },
    "bathroom trash bags":{
        "department": "aisle 24",
        "unit": "box"
    },
    "gallon sized zip-lock bags":{
        "department": "aisle 24",
        "unit": "box"
    },
    "saran wrap":{
        "department": "aisle 24",
        "unit": "box"
    },
    "sandwich sized zip-lock bags":{
        "department": "aisle 24",
        "unit": "box"
    },

    "duster refill":{
        "department": "aisle 26",
        "unit": "box"
    },
    "swiffer wet jet refill":{
        "department": "aisle 26",
        "unit": "box"
    },




    "dishwasher pods":{
        "department": "aisle 27",
        "unit": "package"
    },
    "dawn powerwash refill":{
        "department": "aisle 27",
        "unit": "bottle"
    },
    "dawn dish soap":{
        "department": "aisle 27",
        "unit": "bottle"
    }, 
    
    "laundry detergent":{
        "department": "aisle 28",
        "unit": "jug"
    },

    "cotton rounds":{
        "department": "aisle 34",
        "unit": "package"
    },
    "kaylee conditioner":{
        "department": "aisle 34",
        "unit": "bottle"
    },
    "kaylee shampoo":{
        "department": "aisle 34",
        "unit": "bottle"
    },

    "kaylee bodywash":{
        "department": "aisle 36",
        "unit": "bottle"
    },
    "kaylee deodorant":{
        "department": "aisle 36",
        "unit": "stick"
    },
    "kaylee loofah":{
        "department": "aisle 37",
        "unit": "scrubby scrub"
    },
    "kaylee shaving cream":{
        "department": "aisle 36",
        "unit": "bottle"
    },
    "hand soap":{
        "department": "aisle 36",
        "unit": "bottle"
    },

    "anthony deodorant":{
        "department": "aisle 37",
        "unit": "stick"
    },
    "anthony bodywash":{
        "department": "aisle 37",
        "unit": "bottle"
    },
    "anthony loofah":{
        "department": "aisle 37",
        "unit": "scrubby scrub"
    },
    "anthony shampoo":{
        "department": "aisle 37",
        "unit": "bottle"
    },
    "disposable razors":{
        "department": "aisle 37",
        "unit": "package"
    },

    "toothpaste":{
        "department": "aisle 38",
        "unit": "tube"
    },    
    "dental floss":{
        "department": "aisle 38",
        "unit": "package"
    },
    "Q-tips":{
        "department": "aisle 38",
        "unit": "package"
    },



    "ice cream":{
        "department": "aisle 17",
        "unit": "package"
    },
    "curly fries":{
        "department": "aisle 16",
        "unit": "bag"
    },
    "emergency pizza":{
        "department": "aisle 14",
        "unit": "each"
    },
    "frozen blueberries":{
        "department": "aisle 15",
        "unit": "bag"
    },
    "lasagna":{
        "department": "aisle 15",
        "unit": "box"
    },
    "frozen mango":{
        "department": "aisle 15",
        "unit": "bag"
    },
    "frozen pineapple":{
        "department": "aisle 15",
        "unit": "bag"
    },
    "frozen strawberries":{
        "department": "aisle 15",
        "unit": "bag"
    },
    "garlic bread":{
        "department": "aisle 14",
        "unit": "piece"
    }
    
}
